aliyunsdkrds_data/__init__.py
aliyunsdkrds_data/request/__init__.py
aliyunsdkrds_data/request/v20220330/BatchExecuteStatementRequest.py
aliyunsdkrds_data/request/v20220330/BeginTransactionRequest.py
aliyunsdkrds_data/request/v20220330/CommitTransactionRequest.py
aliyunsdkrds_data/request/v20220330/DeleteRequest.py
aliyunsdkrds_data/request/v20220330/ExecuteStatementRequest.py
aliyunsdkrds_data/request/v20220330/InsertListRequest.py
aliyunsdkrds_data/request/v20220330/InsertRequest.py
aliyunsdkrds_data/request/v20220330/RollbackTransactionRequest.py
aliyunsdkrds_data/request/v20220330/SelectRequest.py
aliyunsdkrds_data/request/v20220330/UpdateRequest.py
aliyunsdkrds_data/request/v20220330/__init__.py
aliyun_python_sdk_rds_data-1.0.0.dist-info/LICENSE
aliyun_python_sdk_rds_data-1.0.0.dist-info/METADATA
aliyun_python_sdk_rds_data-1.0.0.dist-info/WHEEL
aliyun_python_sdk_rds_data-1.0.0.dist-info/top_level.txt
aliyun_python_sdk_rds_data-1.0.0.dist-info/RECORD
